scikick/__init__.py
scikick/config.py
scikick/graph.py
scikick/init.py
scikick/layout.py
scikick/move.py
scikick/scikick.py
scikick/snakemake.py
scikick/status.py
scikick/utils.py
scikick/version.py
scikick/yaml.py
scikick/__pycache__/__init__.cpython-310.pyc
scikick/__pycache__/__init__.cpython-36.pyc
scikick/__pycache__/__init__.cpython-38.pyc
scikick/__pycache__/config.cpython-310.pyc
scikick/__pycache__/config.cpython-36.pyc
scikick/__pycache__/config.cpython-38.pyc
scikick/__pycache__/graph.cpython-310.pyc
scikick/__pycache__/graph.cpython-36.pyc
scikick/__pycache__/graph.cpython-38.pyc
scikick/__pycache__/init.cpython-310.pyc
scikick/__pycache__/init.cpython-36.pyc
scikick/__pycache__/init.cpython-38.pyc
scikick/__pycache__/layout.cpython-310.pyc
scikick/__pycache__/layout.cpython-36.pyc
scikick/__pycache__/layout.cpython-38.pyc
scikick/__pycache__/move.cpython-310.pyc
scikick/__pycache__/move.cpython-38.pyc
scikick/__pycache__/scikick.cpython-310.pyc
scikick/__pycache__/scikick.cpython-38.pyc
scikick/__pycache__/snakemake.cpython-310.pyc
scikick/__pycache__/snakemake.cpython-36.pyc
scikick/__pycache__/snakemake.cpython-38.pyc
scikick/__pycache__/status.cpython-310.pyc
scikick/__pycache__/status.cpython-38.pyc
scikick/__pycache__/utils.cpython-310.pyc
scikick/__pycache__/utils.cpython-36.pyc
scikick/__pycache__/utils.cpython-38.pyc
scikick/__pycache__/version.cpython-310.pyc
scikick/__pycache__/version.cpython-36.pyc
scikick/__pycache__/version.cpython-38.pyc
scikick/__pycache__/yaml.cpython-310.pyc
scikick/__pycache__/yaml.cpython-36.pyc
scikick/__pycache__/yaml.cpython-38.pyc
scikick/demo/PCA.Rmd
scikick/demo/PC_score_statistics.Rmd
scikick/demo/analysis_config.txt
scikick/demo/generate.Rmd
scikick/demo/index.Rmd
scikick/usr/.gitignore
scikick/usr/.gitlab-ci.yml
scikick/usr/README
scikick/usr/requirements.txt
scikick/usr/scikick.yml
scikick/workflow/README.md
scikick/workflow/Snakefile
scikick/workflow/loghandler.py
scikick/workflow/presnakemake.py
scikick-0.2.1.dist-info/LICENSE
scikick-0.2.1.dist-info/METADATA
scikick-0.2.1.dist-info/WHEEL
scikick-0.2.1.dist-info/entry_points.txt
scikick-0.2.1.dist-info/top_level.txt
scikick-0.2.1.dist-info/RECORD
