Metadata-Version: 2.1
Name: scikick
Version: 0.2.1
Summary: Utility for executing collecitons of computational notebooks
Classifier: Programming Language :: Python :: 3.6
Classifier: Programming Language :: Python :: 3.7
Classifier: Programming Language :: Python :: 3.8
Classifier: License :: OSI Approved :: GNU Affero General Public License v3
Classifier: Operating System :: Unix
Classifier: Operating System :: POSIX :: Linux
License-File: LICENSE
Requires-Dist: snakemake (>=5.9.0)
Requires-Dist: ruamel.yaml (>=0.16.5)
Requires-Dist: graphviz (>=0.16)
